hypertune/__init__.py
hypertune/bayesian_search.py
hypertune/grid_search.py
hypertune/hypertune.py
hypertune/random_search.py
tests/__init__.py
tests/test_bayesian_search.py
tests/test_grid_search.py
tests/test_hypertune.py
tests/test_random_search.py
hypertune_param-0.1.1.dist-info/LICENSE
hypertune_param-0.1.1.dist-info/METADATA
hypertune_param-0.1.1.dist-info/WHEEL
hypertune_param-0.1.1.dist-info/top_level.txt
hypertune_param-0.1.1.dist-info/RECORD
