Metadata-Version: 2.2
Name: hypertune-param
Version: 0.1.1
Summary: A custom library for hyperparameter optimization using Grid Search, Random Search, and Bayesian Optimization.
Home-page: https://github.com/Arcoson/hypertune
Author: Arcoson
Author-email: hylendust@gmail.com
Classifier: Programming Language :: Python :: 3
Classifier: License :: OSI Approved :: MIT License
Classifier: Operating System :: OS Independent
Classifier: Intended Audience :: Developers
Requires-Python: >=3.6
License-File: LICENSE
Requires-Dist: scikit-learn==1.2.2
Requires-Dist: hyperopt==0.2.7
Requires-Dist: numpy==1.24.3
Requires-Dist: pandas==1.5.3
Requires-Dist: matplotlib==3.7.1
Dynamic: author
Dynamic: author-email
Dynamic: classifier
Dynamic: description
Dynamic: description-content-type
Dynamic: home-page
Dynamic: requires-dist
Dynamic: requires-python
Dynamic: summary
